v_lczero_bindings-0.31.2.dist-info/RECORD
v_lczero_bindings-0.31.2.dist-info/WHEEL
v_lczero_bindings-0.31.2.dist-info/COPYING
v_lczero_bindings-0.31.2.dist-info/METADATA
v_lczero_bindings-0.31.2.data/headers/eigen3/signature_of_eigen3_matrix_library
v_lczero_bindings-0.31.2.data/headers/eigen3/unsupported/Eigen/MatrixFunctions
v_lczero_bindings-0.31.2.data/headers/eigen3/unsupported/Eigen/AdolcForward
v_lczero_bindings-0.31.2.data/headers/eigen3/unsupported/Eigen/AlignedVector3
v_lczero_bindings-0.31.2.data/headers/eigen3/unsupported/Eigen/OpenGLSupport
v_lczero_bindings-0.31.2.data/headers/eigen3/unsupported/Eigen/LevenbergMarquardt
v_lczero_bindings-0.31.2.data/headers/eigen3/unsupported/Eigen/AutoDiff
v_lczero_bindings-0.31.2.data/headers/eigen3/unsupported/Eigen/NumericalDiff
v_lczero_bindings-0.31.2.data/headers/eigen3/unsupported/Eigen/NonLinearOptimization
v_lczero_bindings-0.31.2.data/headers/eigen3/unsupported/Eigen/ArpackSupport
v_lczero_bindings-0.31.2.data/headers/eigen3/unsupported/Eigen/Skyline
v_lczero_bindings-0.31.2.data/headers/eigen3/unsupported/Eigen/BVH
v_lczero_bindings-0.31.2.data/headers/eigen3/unsupported/Eigen/SpecialFunctions
v_lczero_bindings-0.31.2.data/headers/eigen3/unsupported/Eigen/Splines
v_lczero_bindings-0.31.2.data/headers/eigen3/unsupported/Eigen/KroneckerProduct
v_lczero_bindings-0.31.2.data/headers/eigen3/unsupported/Eigen/IterativeSolvers
v_lczero_bindings-0.31.2.data/headers/eigen3/unsupported/Eigen/FFT
v_lczero_bindings-0.31.2.data/headers/eigen3/unsupported/Eigen/EulerAngles
v_lczero_bindings-0.31.2.data/headers/eigen3/unsupported/Eigen/SparseExtra
v_lczero_bindings-0.31.2.data/headers/eigen3/unsupported/Eigen/Polynomials
v_lczero_bindings-0.31.2.data/headers/eigen3/unsupported/Eigen/MoreVectorization
v_lczero_bindings-0.31.2.data/headers/eigen3/unsupported/Eigen/MPRealSupport
v_lczero_bindings-0.31.2.data/headers/eigen3/unsupported/Eigen/CXX11/ThreadPool
v_lczero_bindings-0.31.2.data/headers/eigen3/unsupported/Eigen/CXX11/TensorSymmetry
v_lczero_bindings-0.31.2.data/headers/eigen3/unsupported/Eigen/CXX11/Tensor
